<annotation>
	<folder>ResizedPhotos.0</folder>
	<filename>IMG_20190311_132032.jpg</filename>
	<path>/Users/admin/Downloads/ResizedPhotos.0/IMG_20190311_132032.jpg</path>
	<source>
		<database>Unknown</database>
	</source>
	<size>
		<width>800</width>
		<height>450</height>
		<depth>3</depth>
	</size>
	<segmented>0</segmented>
	<object>
		<name>drone</name>
		<pose>Unspecified</pose>
		<truncated>0</truncated>
		<difficult>0</difficult>
		<bndbox>
			<xmin>224</xmin>
			<ymin>74</ymin>
			<xmax>237</xmax>
			<ymax>84</ymax>
		</bndbox>
	</object>
</annotation>
